README.rst
calc
setup.cfg
setup.py
pycalc/__init__.py
pycalc/plotting.py
pycalc/units.py
pycalc/version.py
pycalc.egg-info/PKG-INFO
pycalc.egg-info/SOURCES.txt
pycalc.egg-info/dependency_links.txt
pycalc.egg-info/requires.txt
pycalc.egg-info/top_level.txt