Metadata-Version: 1.1
Name: pycalc
Version: 0.0.2
Summary: Use python as a calculator...
Home-page: https://github.com/duerrp/pycalc
Author: Peter Duerr
Author-email: duerrp@gmail.com
License: MIT
Keywords: science
Platform: UNKNOWN
Classifier: Development Status :: 3 - Alpha
Classifier: Topic :: Utilities
Classifier: License :: OSI Approved :: MIT License
Classifier: Programming Language :: Python
Classifier: Programming Language :: Python :: 2.7
Classifier: Programming Language :: Python :: 3.2
Classifier: Programming Language :: Python :: 3.3
Classifier: Programming Language :: Python :: 3.4
Classifier: Programming Language :: Python :: Implementation :: CPython
